chattertools/__init__.py
chattertools/chatter_client.py
chattertools/chatter_requestor.py
chattertools/focas.py
chattertools/focas_structs.py
chattertools/helpers/__init__.py
chattertools/helpers/parsers.py
chattertools/lib/libfwlib32-linux-armv7.so.1.0.5
chattertools/lib/libfwlib32-linux-x64.so.1.0.5
chattertools/lib/libfwlib32-linux-x86.so.1.0.0
chattertools/lib/libfwlib32-linux-x86.so.1.0.5
chattertools/lib/Fwlib64/Fwlib64.dll
chattertools/lib/Fwlib64/Fwlib64.lib
chattertools/lib/Fwlib64/fwlib0DN64.dll
chattertools/lib/Fwlib64/fwlib0iD64.dll
chattertools/lib/Fwlib64/fwlib30i64.dll
chattertools/lib/Fwlib64/fwlibNCG64.dll
chattertools/lib/Fwlib64/fwlibe64.dll
chattertools/models/__init__.py
chattertools/models/data_type.py
chattertools/models/machine.py
chattertools/models/macro.py
chattertools/models/transaction.py
chattertools/services/__init__.py
chattertools/services/machine_service.py
chattertools/services/macro_service.py
chattertools/services/service.py
chattertools/services/state_service.py
chattertools/services/transaction_service.py
chattertools-1.0.0.dist-info/METADATA
chattertools-1.0.0.dist-info/WHEEL
chattertools-1.0.0.dist-info/licenses/LICENSE
chattertools-1.0.0.dist-info/RECORD
