Metadata-Version: 2.3
Name: chattertools
Version: 1.0.0
Summary: A collection of tools for CNC machine related development.
Project-URL: Homepage, https://github.com/Chatter-Software-Development/chattertools
Project-URL: Issues, https://github.com/Chatter-Software-Development/chattertools/issues
Author-email: Pete Oxenham <pete+chattertools@chatter.dev>
License-Expression: Apache-2.0
License-File: LICENSE
Classifier: License :: OSI Approved :: MIT License
Classifier: Operating System :: OS Independent
Classifier: Programming Language :: Python :: 3
Requires-Python: >=3.8
Requires-Dist: requests>=2.31.0
